gdriveresolver/__init__.py
gdriveresolver/exceptions.py
gdriveresolver/model.py
gdriveresolver/resolver.py
gdriveresolver/system_operations.py
gdriveresolver-0.0.16.dist-info/LICENSE
gdriveresolver-0.0.16.dist-info/METADATA
gdriveresolver-0.0.16.dist-info/WHEEL
gdriveresolver-0.0.16.dist-info/top_level.txt
gdriveresolver-0.0.16.dist-info/RECORD
