Metadata-Version: 2.1
Name: gdriveresolver
Version: 0.0.16
Summary: A package that helps resolve relative Google Drive paths to absolute system paths that refer to the Google drive mount location.
Author-email: C Harman <charman@netrias.com>
Project-URL: Homepage, https://github.com/netrias/gdrive_resolver
Project-URL: Issues, https://github.com/netrias/gdrive_resolver/issues
Classifier: Programming Language :: Python :: 3
Classifier: License :: OSI Approved :: MIT License
Classifier: Operating System :: OS Independent
Requires-Python: >=3.8
License-File: LICENSE
